{
  "joinGame": "join_game",
  "startGame": "start_game",
  "selectStarter": "select_starter",
  "rollDice": "roll_dice",
  "movePlayer": "move_player",
  "resolveTile": "resolve_tile",
  "capturePokemon": "capture_pokemon",
  "rollCaptureDice": "roll_capture_dice",
  "passTurn": "pass_turn",
  "skipAction": "skip_action",
  "challengePlayer": "challenge_player",
  "skipChallenge": "skip_action",
  "battleChoice": "battle_choice",
  "rollBattleDice": "roll_battle_dice",
  "removePlayer": "remove_player",
  "leaveGame": "leave_game",
  "saveState": "save_state",
  "restoreState": "restore_state",
  "useAbility": "use_ability",
  "resolveEvent": "resolve_event",
  "resolvePendingAction": "resolve_pending_action",
  "discardItem": "discard_item",
  "releasePokemon": "release_pokemon",
  "useItem": "use_item",
  "debugAddItem": "debug_add_item",
  "debugToggleHostTools": "debug_toggle_host_tools",
  "debugMoveHost": "debug_move_host",
  "debugAddPokemonToHost": "debug_add_pokemon_to_host",
  "debugAddPokemonToTestPlayer": "debug_add_pokemon_to_test_player",
  "debugTriggerCurrentTile": "debug_trigger_current_tile",
  "debugToggleTestPlayer": "debug_toggle_test_player",
  "debugMoveTestPlayer": "debug_move_test_player",
  "debugRollTestPlayer": "debug_roll_test_player",
  "debugTriggerTestPlayerTile": "debug_trigger_test_player_tile",
  "debugRollCaptureForTestPlayer": "debug_roll_capture_for_test_player",
  "debugResolveEventForTestPlayer": "debug_resolve_event_for_test_player",
  "debugSkipTestPlayerPending": "debug_skip_test_player_pending",
  "debugStartDuelWithPlayer": "debug_start_duel_with_player",
  "debugDuelChoosePokemon": "debug_duel_choose_pokemon",
  "debugDuelRollBattle": "debug_duel_roll_battle",
  "debugResolvePendingActionForTestPlayer": "debug_resolve_pending_action_for_test_player",
  "dismissRevealedCard": "dismiss_revealed_card",
  "confirmLeagueIntermission": "confirm_league_intermission"
}
